pypi_notifier/__init__.py
pypi_notifier/config.py
pypi_notifier/database.py
pypi_notifier/logger.py
pypi_notifier/notifier.py
pypi_notifier-0.1.1.dist-info/LICENSE
pypi_notifier-0.1.1.dist-info/METADATA
pypi_notifier-0.1.1.dist-info/WHEEL
pypi_notifier-0.1.1.dist-info/RECORD
