Metadata-Version: 2.1
Name: pypi-notifier
Version: 0.1.1
Summary: Simple utility to parse PyPI packages and send notifications
License: MIT
Keywords: python,notifications,watch,update,pypi,packages
Author: jlw_4049
Author-email: jessielw4049@gmail.com
Maintainer: jlw_4049
Maintainer-email: jessielw4049@gmail.com
Requires-Python: >=3.10,<4.0
Classifier: Development Status :: 5 - Production/Stable
Classifier: Environment :: Console
Classifier: Intended Audience :: Developers
Classifier: License :: OSI Approved :: MIT License
Classifier: Operating System :: OS Independent
Classifier: Programming Language :: Python :: 3
Classifier: Programming Language :: Python :: 3.10
Classifier: Programming Language :: Python :: 3.11
Classifier: Programming Language :: Python :: 3.12
Classifier: Programming Language :: Python :: 3 :: Only
Classifier: Programming Language :: Python :: 3.13
Classifier: Programming Language :: Python :: Implementation :: CPython
Classifier: Topic :: Utilities
Requires-Dist: apscheduler (>=3.11.0,<4.0.0)
Requires-Dist: discord-webhook (>=1.3.1,<2.0.0)
Requires-Dist: feedparser (>=6.0.11,<7.0.0)
Requires-Dist: packaging (>=24.2,<25.0)
Requires-Dist: python-dotenv (>=1.0.1,<2.0.0)
